{
  "generated_at": "2026-06-19T03:34:39.753850+00:00",
  "commit": "bf2147ac",
  "diagnostic_logd": "diagnostic/build-bf2147ac.logd",
  "chunked": false,
  "chunk_size_bytes": null,
  "password": "dc26469f8bbb61583bbf",
  "decrypt_command": "encryptly unpack diagnostic/build-bf2147ac.logd <outdir> --password dc26469f8bbb61583bbf",
  "total_modules": 10,
  "passed": 4,
  "failed": 6,
  "modules": [
    {
      "name": "backend",
      "status": "FAIL",
      "elapsed_seconds": 0,
      "artifact": null
    },
    {
      "name": "frontend",
      "status": "PASS",
      "elapsed_seconds": 5.093,
      "artifact": "/home/coder/errordog-tent-work/frontend/dist"
    },
    {
      "name": "market",
      "status": "PASS",
      "elapsed_seconds": 0.109,
      "artifact": "/home/coder/errordog-tent-work/market/market"
    },
    {
      "name": "frailbox",
      "status": "PASS",
      "elapsed_seconds": 0.003,
      "artifact": "/home/coder/errordog-tent-work/frailbox/frailbox"
    },
    {
      "name": "engine",
      "status": "PASS",
      "elapsed_seconds": 21.141,
      "artifact": "/home/coder/errordog-tent-work/frailbox/engine/build/trial-engine"
    },
    {
      "name": "compliance",
      "status": "FAIL",
      "elapsed_seconds": 0,
      "artifact": null
    },
    {
      "name": "v2-market-stream",
      "status": "FAIL",
      "elapsed_seconds": 0,
      "artifact": null
    },
    {
      "name": "nfc-scanner",
      "status": "FAIL",
      "elapsed_seconds": 0,
      "artifact": null
    },
    {
      "name": "openapi-haskell",
      "status": "FAIL",
      "elapsed_seconds": 0,
      "artifact": null
    },
    {
      "name": "openapi-tools",
      "status": "FAIL",
      "elapsed_seconds": 0,
      "artifact": null
    }
  ],
  "pr_note": "Include this metadata and diagnostic/build-bf2147ac.logd in your PR. Maintainers may ask you to remove these diagnostic artifacts before merging."
}
